quanteda/__init__.py
quanteda/generate_financial_metrics.py
quanteda/generate_return_series.py
quanteda/plot_missing_vals.py
quanteda/plot_num_dist.py
quanteda-3.0.0.dist-info/LICENSE
quanteda-3.0.0.dist-info/METADATA
quanteda-3.0.0.dist-info/WHEEL
quanteda-3.0.0.dist-info/RECORD
