Metadata-Version: 2.1
Name: quanteda
Version: 3.0.0
Summary: Perform exploratory data analysis (EDA) on quantitative data.
License: MIT
Author: Doris (Yun Yi) Cai, Jake Barnabe, John Shiu, Merete Lutz
Requires-Python: >=3.9,<4.0
Classifier: License :: OSI Approved :: MIT License
Classifier: Programming Language :: Python :: 3
Classifier: Programming Language :: Python :: 3.9
Classifier: Programming Language :: Python :: 3.10
Classifier: Programming Language :: Python :: 3.11
Classifier: Programming Language :: Python :: 3.12
Requires-Dist: altair (==5.2.0)
Requires-Dist: pandas (==2.1.4)
